polaroid-0.3.2.dist-info/WHEEL
polaroid-0.3.2.dist-info/top_level.txt
polaroid-0.3.2.dist-info/RECORD
polaroid-0.3.2.dist-info/METADATA
polaroid-0.3.2.dist-info/LICENSE
polaroid/polaroid.cpython-39-x86_64-linux-gnu.so
polaroid/__init__.py
