Metadata-Version: 2.1
Name: polaroid
Version: 0.3.2
Summary: Hyper Fast and safe image manipulation library for python. Powered by rust.
Home-page: https://github.com/Daggy1234/polaroid
Author: Daggy1234
License: MIT
Project-URL: Repository, https://github.com/Daggy1234/polaroid
Project-URL: Issue tracker, https://github.com/Daggy1234/polaroid/issues
Project-URL: Chat, https://server.daggy.tech
Platform: UNKNOWN
Classifier: Intended Audience :: Developers
Classifier: License :: OSI Approved :: MIT License
Classifier: Development Status :: 3 - Alpha
Classifier: Intended Audience :: Developers
Classifier: Programming Language :: Python
Classifier: Programming Language :: Rust
Classifier: Operating System :: OS Independent
Classifier: Natural Language :: English
Classifier: Programming Language :: Python :: 3.6
Classifier: Programming Language :: Python :: 3.7
Classifier: Programming Language :: Python :: 3.8
Classifier: Programming Language :: Python :: 3.9
Classifier: Topic :: Internet
Classifier: Topic :: Software Development :: Libraries
Classifier: Topic :: Software Development :: Libraries :: Python Modules
Classifier: Topic :: Utilities
Requires-Python: >=3.6
